FUNC.cpython-39-x86_64-linux-gnu.so
PyAGH/__init__.py
PyAGH/amatrix.py
PyAGH/coef.py
PyAGH/gmatrix.py
PyAGH/hmatrix.py
PyAGH/inter_matrix.py
PyAGH/loaddata.py
PyAGH/mmatrix.py
PyAGH/plot.py
PyAGH/selectped.py
PyAGH/sort.py
PyAGH/data/geno.traw
PyAGH/data/ped.txt
PyAGH-0.3.3.dist-info/LICENSE
PyAGH-0.3.3.dist-info/METADATA
PyAGH-0.3.3.dist-info/WHEEL
PyAGH-0.3.3.dist-info/top_level.txt
PyAGH-0.3.3.dist-info/RECORD
